[
  {
    "transactionId": 0,
    "customer": {
      "customerId": 1,
      "customerName": "John Doe"
    },
    "amount": 293,
    "currency": "USD",
    "transactionDate": "2022-03-08",
    "productName": "Intelligent Wooden Chair"
  },
  {
    "transactionId": 1,
    "customer": {
      "customerId": 5,
      "customerName": "David Hamilton"
    },
    "amount": 123,
    "currency": "USD",
    "transactionDate": "2022-03-11",
    "productName": "Fantastic Cotton Towels"
  },
  {
    "transactionId": 2,
    "customer": {
      "customerId": 1,
      "customerName": "John Doe"
    },
    "amount": 351,
    "currency": "USD",
    "transactionDate": "2022-02-01",
    "productName": "Small Plastic Sausages"
  },
  {
    "transactionId": 3,
    "customer": {
      "customerId": 1,
      "customerName": "John Doe"
    },
    "amount": 284,
    "currency": "USD",
    "transactionDate": "2022-03-19",
    "productName": "Rustic Rubber Tuna"
  },
  {
    "transactionId": 4,
    "customer": {
      "customerId": 3,
      "customerName": "Andrew Black"
    },
    "amount": 180,
    "currency": "USD",
    "transactionDate": "2022-03-03",
    "productName": "Small Metal Gloves"
  },
  {
    "transactionId": 5,
    "customer": {
      "customerId": 4,
      "customerName": "Alan McGee"
    },
    "amount": 89,
    "currency": "USD",
    "transactionDate": "2022-01-27",
    "productName": "Unbranded Fresh Pizza"
  },
  {
    "transactionId": 6,
    "customer": {
      "customerId": 1,
      "customerName": "John Doe"
    },
    "amount": 220,
    "currency": "USD",
    "transactionDate": "2022-03-20",
    "productName": "Handmade Metal Gloves"
  },
  {
    "transactionId": 7,
    "customer": {
      "customerId": 5,
      "customerName": "David Hamilton"
    },
    "amount": 74,
    "currency": "USD",
    "transactionDate": "2022-03-06",
    "productName": "Gorgeous Soft Gloves"
  },
  {
    "transactionId": 8,
    "customer": {
      "customerId": 2,
      "customerName": "Mary Pope"
    },
    "amount": 479,
    "currency": "USD",
    "transactionDate": "2022-03-27",
    "productName": "Tasty Cotton Computer"
  },
  {
    "transactionId": 9,
    "customer": {
      "customerId": 4,
      "customerName": "Alan McGee"
    },
    "amount": 29,
    "currency": "USD",
    "transactionDate": "2022-02-06",
    "productName": "Gorgeous Fresh Sausages"
  },
  {
    "transactionId": 10,
    "customer": {
      "customerId": 4,
      "customerName": "Alan McGee"
    },
    "amount": 19,
    "currency": "USD",
    "transactionDate": "2022-03-21",
    "productName": "Fantastic Fresh Ball"
  },
  {
    "transactionId": 11,
    "customer": {
      "customerId": 4,
      "customerName": "Alan McGee"
    },
    "amount": 324,
    "currency": "USD",
    "transactionDate": "2022-03-16",
    "productName": "Small Concrete Bike"
  },
  {
    "transactionId": 12,
    "customer": {
      "customerId": 2,
      "customerName": "Mary Pope"
    },
    "amount": 71,
    "currency": "USD",
    "transactionDate": "2022-02-25",
    "productName": "Refined Rubber Pizza"
  },
  {
    "transactionId": 13,
    "customer": {
      "customerId": 5,
      "customerName": "David Hamilton"
    },
    "amount": 380,
    "currency": "USD",
    "transactionDate": "2022-02-17",
    "productName": "Gorgeous Granite Hat"
  },
  {
    "transactionId": 14,
    "customer": {
      "customerId": 3,
      "customerName": "Andrew Black"
    },
    "amount": 406,
    "currency": "USD",
    "transactionDate": "2022-02-28",
    "productName": "Intelligent Concrete Table"
  },
  {
    "transactionId": 15,
    "customer": {
      "customerId": 5,
      "customerName": "David Hamilton"
    },
    "amount": 335,
    "currency": "USD",
    "transactionDate": "2022-03-08",
    "productName": "Refined Steel Table"
  },
  {
    "transactionId": 16,
    "customer": {
      "customerId": 1,
      "customerName": "John Doe"
    },
    "amount": 303,
    "currency": "USD",
    "transactionDate": "2022-03-12",
    "productName": "Sleek Plastic Gloves"
  },
  {
    "transactionId": 17,
    "customer": {
      "customerId": 5,
      "customerName": "David Hamilton"
    },
    "amount": 135,
    "currency": "USD",
    "transactionDate": "2022-03-17",
    "productName": "Incredible Granite Keyboard"
  },
  {
    "transactionId": 18,
    "customer": {
      "customerId": 2,
      "customerName": "Mary Pope"
    },
    "amount": 251,
    "currency": "USD",
    "transactionDate": "2022-02-18",
    "productName": "Incredible Plastic Keyboard"
  },
  {
    "transactionId": 19,
    "customer": {
      "customerId": 1,
      "customerName": "John Doe"
    },
    "amount": 372,
    "currency": "USD",
    "transactionDate": "2022-03-09",
    "productName": "Tasty Cotton Chips"
  },
  {
    "transactionId": 20,
    "customer": {
      "customerId": 5,
      "customerName": "David Hamilton"
    },
    "amount": 217,
    "currency": "USD",
    "transactionDate": "2022-03-10",
    "productName": "Generic Metal Fish"
  },
  {
    "transactionId": 21,
    "customer": {
      "customerId": 2,
      "customerName": "Mary Pope"
    },
    "amount": 96,
    "currency": "USD",
    "transactionDate": "2022-03-20",
    "productName": "Ergonomic Cotton Shirt"
  },
  {
    "transactionId": 22,
    "customer": {
      "customerId": 3,
      "customerName": "Andrew Black"
    },
    "amount": 329,
    "currency": "USD",
    "transactionDate": "2022-03-19",
    "productName": "Intelligent Fresh Chicken"
  },
  {
    "transactionId": 23,
    "customer": {
      "customerId": 5,
      "customerName": "David Hamilton"
    },
    "amount": 209,
    "currency": "USD",
    "transactionDate": "2022-02-11",
    "productName": "Unbranded Concrete Shoes"
  },
  {
    "transactionId": 24,
    "customer": {
      "customerId": 4,
      "customerName": "Alan McGee"
    },
    "amount": 492,
    "currency": "USD",
    "transactionDate": "2022-03-01",
    "productName": "Generic Fresh Mouse"
  },
  {
    "transactionId": 25,
    "customer": {
      "customerId": 2,
      "customerName": "Mary Pope"
    },
    "amount": 301,
    "currency": "USD",
    "transactionDate": "2022-03-15",
    "productName": "Sleek Granite Pizza"
  },
  {
    "transactionId": 26,
    "customer": {
      "customerId": 1,
      "customerName": "John Doe"
    },
    "amount": 115,
    "currency": "USD",
    "transactionDate": "2022-03-15",
    "productName": "Generic Cotton Shirt"
  },
  {
    "transactionId": 27,
    "customer": {
      "customerId": 2,
      "customerName": "Mary Pope"
    },
    "amount": 418,
    "currency": "USD",
    "transactionDate": "2022-03-10",
    "productName": "Handcrafted Plastic Computer"
  },
  {
    "transactionId": 28,
    "customer": {
      "customerId": 3,
      "customerName": "Andrew Black"
    },
    "amount": 369,
    "currency": "USD",
    "transactionDate": "2022-03-18",
    "productName": "Small Soft Mouse"
  },
  {
    "transactionId": 29,
    "customer": {
      "customerId": 1,
      "customerName": "John Doe"
    },
    "amount": 158,
    "currency": "USD",
    "transactionDate": "2022-01-28",
    "productName": "Small Fresh Table"
  },
  {
    "transactionId": 30,
    "customer": {
      "customerId": 5,
      "customerName": "David Hamilton"
    },
    "amount": 19,
    "currency": "USD",
    "transactionDate": "2022-03-08",
    "productName": "Intelligent Concrete Table"
  },
  {
    "transactionId": 31,
    "customer": {
      "customerId": 2,
      "customerName": "Mary Pope"
    },
    "amount": 451,
    "currency": "USD",
    "transactionDate": "2022-02-18",
    "productName": "Awesome Rubber Fish"
  },
  {
    "transactionId": 32,
    "customer": {
      "customerId": 5,
      "customerName": "David Hamilton"
    },
    "amount": 90,
    "currency": "USD",
    "transactionDate": "2022-03-18",
    "productName": "Handcrafted Steel Soap"
  },
  {
    "transactionId": 33,
    "customer": {
      "customerId": 2,
      "customerName": "Mary Pope"
    },
    "amount": 435,
    "currency": "USD",
    "transactionDate": "2022-03-06",
    "productName": "Small Cotton Soap"
  },
  {
    "transactionId": 34,
    "customer": {
      "customerId": 2,
      "customerName": "Mary Pope"
    },
    "amount": 12,
    "currency": "USD",
    "transactionDate": "2022-02-21",
    "productName": "Small Cotton Shoes"
  },
  {
    "transactionId": 35,
    "customer": {
      "customerId": 2,
      "customerName": "Mary Pope"
    },
    "amount": 182,
    "currency": "USD",
    "transactionDate": "2022-03-08",
    "productName": "Refined Steel Chair"
  },
  {
    "transactionId": 36,
    "customer": {
      "customerId": 5,
      "customerName": "David Hamilton"
    },
    "amount": 246,
    "currency": "USD",
    "transactionDate": "2022-03-11",
    "productName": "Ergonomic Steel Ball"
  },
  {
    "transactionId": 37,
    "customer": {
      "customerId": 5,
      "customerName": "David Hamilton"
    },
    "amount": 352,
    "currency": "USD",
    "transactionDate": "2022-02-06",
    "productName": "Fantastic Concrete Keyboard"
  },
  {
    "transactionId": 38,
    "customer": {
      "customerId": 1,
      "customerName": "John Doe"
    },
    "amount": 223,
    "currency": "USD",
    "transactionDate": "2022-03-04",
    "productName": "Intelligent Metal Bike"
  },
  {
    "transactionId": 39,
    "customer": {
      "customerId": 4,
      "customerName": "Alan McGee"
    },
    "amount": 440,
    "currency": "USD",
    "transactionDate": "2022-03-14",
    "productName": "Fantastic Wooden Hat"
  },
  {
    "transactionId": 40,
    "customer": {
      "customerId": 5,
      "customerName": "David Hamilton"
    },
    "amount": 311,
    "currency": "USD",
    "transactionDate": "2022-03-05",
    "productName": "Licensed Metal Pants"
  },
  {
    "transactionId": 41,
    "customer": {
      "customerId": 5,
      "customerName": "David Hamilton"
    },
    "amount": 184,
    "currency": "USD",
    "transactionDate": "2022-02-12",
    "productName": "Licensed Steel Keyboard"
  },
  {
    "transactionId": 42,
    "customer": {
      "customerId": 3,
      "customerName": "Andrew Black"
    },
    "amount": 115,
    "currency": "USD",
    "transactionDate": "2022-03-05",
    "productName": "Unbranded Rubber Cheese"
  },
  {
    "transactionId": 43,
    "customer": {
      "customerId": 2,
      "customerName": "Mary Pope"
    },
    "amount": 285,
    "currency": "USD",
    "transactionDate": "2022-03-13",
    "productName": "Ergonomic Granite Gloves"
  },
  {
    "transactionId": 44,
    "customer": {
      "customerId": 2,
      "customerName": "Mary Pope"
    },
    "amount": 338,
    "currency": "USD",
    "transactionDate": "2022-02-06",
    "productName": "Unbranded Granite Chips"
  },
  {
    "transactionId": 45,
    "customer": {
      "customerId": 2,
      "customerName": "Mary Pope"
    },
    "amount": 237,
    "currency": "USD",
    "transactionDate": "2022-02-23",
    "productName": "Licensed Cotton Cheese"
  },
  {
    "transactionId": 46,
    "customer": {
      "customerId": 2,
      "customerName": "Mary Pope"
    },
    "amount": 258,
    "currency": "USD",
    "transactionDate": "2022-02-21",
    "productName": "Licensed Fresh Soap"
  },
  {
    "transactionId": 47,
    "customer": {
      "customerId": 3,
      "customerName": "Andrew Black"
    },
    "amount": 50,
    "currency": "USD",
    "transactionDate": "2022-02-09",
    "productName": "Small Fresh Bacon"
  },
  {
    "transactionId": 48,
    "customer": {
      "customerId": 3,
      "customerName": "Andrew Black"
    },
    "amount": 404,
    "currency": "USD",
    "transactionDate": "2022-02-08",
    "productName": "Small Steel Pizza"
  },
  {
    "transactionId": 49,
    "customer": {
      "customerId": 1,
      "customerName": "John Doe"
    },
    "amount": 495,
    "currency": "USD",
    "transactionDate": "2022-02-22",
    "productName": "Unbranded Cotton Chair"
  },
  {
    "transactionId": 50,
    "customer": {
      "customerId": 5,
      "customerName": "David Hamilton"
    },
    "amount": 331,
    "currency": "USD",
    "transactionDate": "2022-03-21",
    "productName": "Ergonomic Steel Chicken"
  },
  {
    "transactionId": 51,
    "customer": {
      "customerId": 5,
      "customerName": "David Hamilton"
    },
    "amount": 225,
    "currency": "USD",
    "transactionDate": "2022-02-04",
    "productName": "Generic Metal Ball"
  },
  {
    "transactionId": 52,
    "customer": {
      "customerId": 3,
      "customerName": "Andrew Black"
    },
    "amount": 101,
    "currency": "USD",
    "transactionDate": "2022-02-20",
    "productName": "Incredible Wooden Towels"
  },
  {
    "transactionId": 53,
    "customer": {
      "customerId": 4,
      "customerName": "Alan McGee"
    },
    "amount": 206,
    "currency": "USD",
    "transactionDate": "2022-03-19",
    "productName": "Sleek Rubber Soap"
  },
  {
    "transactionId": 54,
    "customer": {
      "customerId": 2,
      "customerName": "Mary Pope"
    },
    "amount": 224,
    "currency": "USD",
    "transactionDate": "2022-03-15",
    "productName": "Gorgeous Concrete Pants"
  },
  {
    "transactionId": 55,
    "customer": {
      "customerId": 4,
      "customerName": "Alan McGee"
    },
    "amount": 116,
    "currency": "USD",
    "transactionDate": "2022-03-20",
    "productName": "Sleek Concrete Chicken"
  },
  {
    "transactionId": 56,
    "customer": {
      "customerId": 3,
      "customerName": "Andrew Black"
    },
    "amount": 294,
    "currency": "USD",
    "transactionDate": "2022-03-15",
    "productName": "Ergonomic Fresh Towels"
  },
  {
    "transactionId": 57,
    "customer": {
      "customerId": 5,
      "customerName": "David Hamilton"
    },
    "amount": 78,
    "currency": "USD",
    "transactionDate": "2022-03-09",
    "productName": "Licensed Cotton Tuna"
  },
  {
    "transactionId": 58,
    "customer": {
      "customerId": 2,
      "customerName": "Mary Pope"
    },
    "amount": 62,
    "currency": "USD",
    "transactionDate": "2022-02-15",
    "productName": "Generic Frozen Soap"
  },
  {
    "transactionId": 59,
    "customer": {
      "customerId": 4,
      "customerName": "Alan McGee"
    },
    "amount": 115,
    "currency": "USD",
    "transactionDate": "2022-03-21",
    "productName": "Refined Soft Bacon"
  },
  {
    "transactionId": 60,
    "customer": {
      "customerId": 1,
      "customerName": "John Doe"
    },
    "amount": 326,
    "currency": "USD",
    "transactionDate": "2022-03-11",
    "productName": "Gorgeous Concrete Fish"
  },
  {
    "transactionId": 61,
    "customer": {
      "customerId": 3,
      "customerName": "Andrew Black"
    },
    "amount": 231,
    "currency": "USD",
    "transactionDate": "2022-03-15",
    "productName": "Sleek Plastic Bacon"
  },
  {
    "transactionId": 62,
    "customer": {
      "customerId": 5,
      "customerName": "David Hamilton"
    },
    "amount": 33,
    "currency": "USD",
    "transactionDate": "2022-03-11",
    "productName": "Gorgeous Frozen Bike"
  },
  {
    "transactionId": 63,
    "customer": {
      "customerId": 2,
      "customerName": "Mary Pope"
    },
    "amount": 444,
    "currency": "USD",
    "transactionDate": "2022-03-08",
    "productName": "Rustic Soft Keyboard"
  },
  {
    "transactionId": 64,
    "customer": {
      "customerId": 3,
      "customerName": "Andrew Black"
    },
    "amount": 448,
    "currency": "USD",
    "transactionDate": "2022-03-10",
    "productName": "Gorgeous Plastic Fish"
  },
  {
    "transactionId": 65,
    "customer": {
      "customerId": 4,
      "customerName": "Alan McGee"
    },
    "amount": 426,
    "currency": "USD",
    "transactionDate": "2022-02-25",
    "productName": "Refined Metal Shirt"
  },
  {
    "transactionId": 66,
    "customer": {
      "customerId": 2,
      "customerName": "Mary Pope"
    },
    "amount": 470,
    "currency": "USD",
    "transactionDate": "2022-03-28",
    "productName": "Handmade Concrete Keyboard"
  },
  {
    "transactionId": 67,
    "customer": {
      "customerId": 3,
      "customerName": "Andrew Black"
    },
    "amount": 469,
    "currency": "USD",
    "transactionDate": "2022-03-18",
    "productName": "Generic Granite Soap"
  },
  {
    "transactionId": 68,
    "customer": {
      "customerId": 4,
      "customerName": "Alan McGee"
    },
    "amount": 143,
    "currency": "USD",
    "transactionDate": "2022-02-21",
    "productName": "Fantastic Rubber Sausages"
  },
  {
    "transactionId": 69,
    "customer": {
      "customerId": 3,
      "customerName": "Andrew Black"
    },
    "amount": 278,
    "currency": "USD",
    "transactionDate": "2022-02-22",
    "productName": "Sleek Steel Shoes"
  },
  {
    "transactionId": 70,
    "customer": {
      "customerId": 5,
      "customerName": "David Hamilton"
    },
    "amount": 470,
    "currency": "USD",
    "transactionDate": "2022-03-02",
    "productName": "Unbranded Plastic Computer"
  },
  {
    "transactionId": 71,
    "customer": {
      "customerId": 4,
      "customerName": "Alan McGee"
    },
    "amount": 299,
    "currency": "USD",
    "transactionDate": "2022-03-07",
    "productName": "Gorgeous Frozen Car"
  },
  {
    "transactionId": 72,
    "customer": {
      "customerId": 3,
      "customerName": "Andrew Black"
    },
    "amount": 324,
    "currency": "USD",
    "transactionDate": "2022-03-03",
    "productName": "Generic Frozen Ball"
  },
  {
    "transactionId": 73,
    "customer": {
      "customerId": 3,
      "customerName": "Andrew Black"
    },
    "amount": 220,
    "currency": "USD",
    "transactionDate": "2022-02-06",
    "productName": "Licensed Frozen Chair"
  },
  {
    "transactionId": 74,
    "customer": {
      "customerId": 2,
      "customerName": "Mary Pope"
    },
    "amount": 333,
    "currency": "USD",
    "transactionDate": "2022-01-26",
    "productName": "Fantastic Wooden Sausages"
  },
  {
    "transactionId": 75,
    "customer": {
      "customerId": 3,
      "customerName": "Andrew Black"
    },
    "amount": 36,
    "currency": "USD",
    "transactionDate": "2022-03-18",
    "productName": "Awesome Steel Sausages"
  },
  {
    "transactionId": 76,
    "customer": {
      "customerId": 2,
      "customerName": "Mary Pope"
    },
    "amount": 377,
    "currency": "USD",
    "transactionDate": "2022-03-16",
    "productName": "Handcrafted Concrete Cheese"
  },
  {
    "transactionId": 77,
    "customer": {
      "customerId": 5,
      "customerName": "David Hamilton"
    },
    "amount": 235,
    "currency": "USD",
    "transactionDate": "2022-03-23",
    "productName": "Tasty Plastic Hat"
  },
  {
    "transactionId": 78,
    "customer": {
      "customerId": 1,
      "customerName": "John Doe"
    },
    "amount": 418,
    "currency": "USD",
    "transactionDate": "2022-02-08",
    "productName": "Rustic Fresh Table"
  },
  {
    "transactionId": 79,
    "customer": {
      "customerId": 5,
      "customerName": "David Hamilton"
    },
    "amount": 373,
    "currency": "USD",
    "transactionDate": "2022-02-18",
    "productName": "Gorgeous Granite Pizza"
  },
  {
    "transactionId": 80,
    "customer": {
      "customerId": 3,
      "customerName": "Andrew Black"
    },
    "amount": 52,
    "currency": "USD",
    "transactionDate": "2022-02-06",
    "productName": "Licensed Rubber Shirt"
  },
  {
    "transactionId": 81,
    "customer": {
      "customerId": 5,
      "customerName": "David Hamilton"
    },
    "amount": 184,
    "currency": "USD",
    "transactionDate": "2022-01-30",
    "productName": "Unbranded Cotton Tuna"
  },
  {
    "transactionId": 82,
    "customer": {
      "customerId": 4,
      "customerName": "Alan McGee"
    },
    "amount": 397,
    "currency": "USD",
    "transactionDate": "2022-03-13",
    "productName": "Ergonomic Metal Bike"
  },
  {
    "transactionId": 83,
    "customer": {
      "customerId": 1,
      "customerName": "John Doe"
    },
    "amount": 451,
    "currency": "USD",
    "transactionDate": "2022-03-06",
    "productName": "Licensed Wooden Mouse"
  },
  {
    "transactionId": 84,
    "customer": {
      "customerId": 2,
      "customerName": "Mary Pope"
    },
    "amount": 294,
    "currency": "USD",
    "transactionDate": "2022-01-27",
    "productName": "Tasty Rubber Chips"
  },
  {
    "transactionId": 85,
    "customer": {
      "customerId": 4,
      "customerName": "Alan McGee"
    },
    "amount": 465,
    "currency": "USD",
    "transactionDate": "2022-02-15",
    "productName": "Sleek Cotton Bacon"
  },
  {
    "transactionId": 86,
    "customer": {
      "customerId": 5,
      "customerName": "David Hamilton"
    },
    "amount": 51,
    "currency": "USD",
    "transactionDate": "2022-02-22",
    "productName": "Ergonomic Soft Chicken"
  },
  {
    "transactionId": 87,
    "customer": {
      "customerId": 1,
      "customerName": "John Doe"
    },
    "amount": 253,
    "currency": "USD",
    "transactionDate": "2022-02-18",
    "productName": "Licensed Frozen Chips"
  },
  {
    "transactionId": 88,
    "customer": {
      "customerId": 5,
      "customerName": "David Hamilton"
    },
    "amount": 264,
    "currency": "USD",
    "transactionDate": "2022-03-20",
    "productName": "Handcrafted Plastic Mouse"
  },
  {
    "transactionId": 89,
    "customer": {
      "customerId": 4,
      "customerName": "Alan McGee"
    },
    "amount": 485,
    "currency": "USD",
    "transactionDate": "2022-02-18",
    "productName": "Refined Frozen Cheese"
  },
  {
    "transactionId": 90,
    "customer": {
      "customerId": 5,
      "customerName": "David Hamilton"
    },
    "amount": 483,
    "currency": "USD",
    "transactionDate": "2022-03-30",
    "productName": "Licensed Soft Fish"
  },
  {
    "transactionId": 91,
    "customer": {
      "customerId": 1,
      "customerName": "John Doe"
    },
    "amount": 497,
    "currency": "USD",
    "transactionDate": "2022-02-06",
    "productName": "Gorgeous Frozen Chair"
  },
  {
    "transactionId": 92,
    "customer": {
      "customerId": 2,
      "customerName": "Mary Pope"
    },
    "amount": 321,
    "currency": "USD",
    "transactionDate": "2022-02-11",
    "productName": "Unbranded Fresh Ball"
  },
  {
    "transactionId": 93,
    "customer": {
      "customerId": 4,
      "customerName": "Alan McGee"
    },
    "amount": 174,
    "currency": "USD",
    "transactionDate": "2022-02-30",
    "productName": "Generic Cotton Cheese"
  },
  {
    "transactionId": 94,
    "customer": {
      "customerId": 2,
      "customerName": "Mary Pope"
    },
    "amount": 415,
    "currency": "USD",
    "transactionDate": "2022-03-29",
    "productName": "Generic Fresh Cheese"
  },
  {
    "transactionId": 95,
    "customer": {
      "customerId": 2,
      "customerName": "Mary Pope"
    },
    "amount": 311,
    "currency": "USD",
    "transactionDate": "2022-01-22",
    "productName": "Licensed Steel Pants"
  },
  {
    "transactionId": 96,
    "customer": {
      "customerId": 4,
      "customerName": "Alan McGee"
    },
    "amount": 205,
    "currency": "USD",
    "transactionDate": "2022-03-03",
    "productName": "Licensed Concrete Chicken"
  },
  {
    "transactionId": 97,
    "customer": {
      "customerId": 2,
      "customerName": "Mary Pope"
    },
    "amount": 308,
    "currency": "USD",
    "transactionDate": "2022-03-06",
    "productName": "Refined Metal Chair"
  },
  {
    "transactionId": 98,
    "customer": {
      "customerId": 2,
      "customerName": "Mary Pope"
    },
    "amount": 430,
    "currency": "USD",
    "transactionDate": "2022-03-01",
    "productName": "Rustic Fresh Pants"
  },
  {
    "transactionId": 99,
    "customer": {
      "customerId": 3,
      "customerName": "Andrew Black"
    },
    "amount": 386,
    "currency": "USD",
    "transactionDate": "2022-03-19",
    "productName": "Refined Metal Hat"
  }
]
